aleksis/apps/tezor/__init__.py
aleksis/apps/tezor/apps.py
aleksis/apps/tezor/filters.py
aleksis/apps/tezor/forms.py
aleksis/apps/tezor/locale/.keepdir
aleksis/apps/tezor/locale/de_DE/LC_MESSAGES/django.mo
aleksis/apps/tezor/locale/de_DE/LC_MESSAGES/django.po
aleksis/apps/tezor/menus.py
aleksis/apps/tezor/migrations/0001_initial.py
aleksis/apps/tezor/migrations/0002_invoice_due_date.py
aleksis/apps/tezor/migrations/0003_manual_invoicing.py
aleksis/apps/tezor/migrations/0004_client_email.py
aleksis/apps/tezor/migrations/0005_alter_fields_invoice.py
aleksis/apps/tezor/migrations/0006_invoice_constraints.py
aleksis/apps/tezor/migrations/0007_client_payment_variants.py
aleksis/apps/tezor/migrations/0008_always_set_person.py
aleksis/apps/tezor/migrations/0009_invoice_billing_phone.py
aleksis/apps/tezor/migrations/__init__.py
aleksis/apps/tezor/models/__init__.py
aleksis/apps/tezor/models/base.py
aleksis/apps/tezor/models/invoice.py
aleksis/apps/tezor/predicates.py
aleksis/apps/tezor/preferences.py
aleksis/apps/tezor/rules.py
aleksis/apps/tezor/settings.py
aleksis/apps/tezor/signals.py
aleksis/apps/tezor/static/.keepdir
aleksis/apps/tezor/tables.py
aleksis/apps/tezor/tasks.py
aleksis/apps/tezor/templates/templated_email/invoice.email
aleksis/apps/tezor/templates/tezor/client/create.html
aleksis/apps/tezor/templates/tezor/client/edit.html
aleksis/apps/tezor/templates/tezor/client/full.html
aleksis/apps/tezor/templates/tezor/client/list.html
aleksis/apps/tezor/templates/tezor/invoice/full.html
aleksis/apps/tezor/templates/tezor/invoice/payment.html
aleksis/apps/tezor/templates/tezor/invoice_group/create.html
aleksis/apps/tezor/templates/tezor/invoice_group/edit.html
aleksis/apps/tezor/templates/tezor/invoice_group/full.html
aleksis/apps/tezor/urls.py
aleksis/apps/tezor/util/__init__.py
aleksis/apps/tezor/util/invoice.py
aleksis/apps/tezor/views.py
aleksis_app_tezor-1.2.dist-info/entry_points.txt
aleksis_app_tezor-1.2.dist-info/WHEEL
aleksis_app_tezor-1.2.dist-info/METADATA
aleksis_app_tezor-1.2.dist-info/RECORD
