Metadata-Version: 2.1
Name: aleksis-app-tezor
Version: 1.2
Summary: AlekSIS (School Information System) — App Tezor (account and payment system)
Home-page: https://aleksis.org
License: EUPL-1.2-or-later
Author: Dominik George
Author-email: dominik.george@teckids.org
Requires-Python: >=3.9,<4.0
Classifier: Environment :: Web Environment
Classifier: Intended Audience :: Education
Classifier: License :: Other/Proprietary License
Classifier: Programming Language :: Python :: 3
Classifier: Programming Language :: Python :: 3.10
Classifier: Programming Language :: Python :: 3.9
Classifier: Topic :: Education
Requires-Dist: aleksis-core (>=2.8.1.dev0,<3.0.0)
Requires-Dist: django-payments-sepa (>=1.0.1,<2.0.0)
Requires-Dist: django-payments[sofort] (>=1.0.0,<2.0.0)
Project-URL: Documentation, https://aleksis.org/official/AlekSIS/docs/html/
Project-URL: Repository, https://edugit.org/AlekSIS/onboarding//AlekSIS-App-Tezor
